pypomes_events/__init__.py
pypomes_events/mq_publisher.py
pypomes_events/mq_subscriber.py
pypomes_events/publisher_pomes.py
pypomes_events/subscriber_pomes.py
pypomes_events-0.1.2.dist-info/METADATA
pypomes_events-0.1.2.dist-info/WHEEL
pypomes_events-0.1.2.dist-info/licenses/LICENSE
pypomes_events-0.1.2.dist-info/RECORD
