Metadata-Version: 2.1
Name: pypomes_events
Version: 0.1.2
Summary: A collection of Python pomes, pennyeach (event handling modules)
Project-URL: Homepage, https://github.com/TheWiseCoder/PyPomes-Events
Project-URL: Bug Tracker, https://github.com/TheWiseCoder/PyPomes-Events/issues
Author-email: GT Nunes <wisecoder01@gmail.com>
License-File: LICENSE
Classifier: License :: OSI Approved :: MIT License
Classifier: Operating System :: OS Independent
Classifier: Programming Language :: Python :: 3
Requires-Python: >=3.10
Requires-Dist: asn1crypto>=1.5.1
Requires-Dist: pika>=1.3.2
Requires-Dist: pip>=23.2.1
Requires-Dist: pypomes-core>=0.2.3
Requires-Dist: setuptools>=68.0.0
Requires-Dist: wheel>=0.41.0
